openapi_client/__init__.py
openapi_client/api_client.py
openapi_client/api_response.py
openapi_client/configuration.py
openapi_client/exceptions.py
openapi_client/py.typed
openapi_client/rest.py
openapi_client/api/__init__.py
openapi_client/api/openapi_api.py
openapi_client/api/slurm_api.py
openapi_client/models/__init__.py
openapi_client/models/v0038_diag.py
openapi_client/models/v0038_diag_rpcm.py
openapi_client/models/v0038_diag_rpcu.py
openapi_client/models/v0038_diag_statistics.py
openapi_client/models/v0038_error.py
openapi_client/models/v0038_job_properties.py
openapi_client/models/v0038_job_resources.py
openapi_client/models/v0038_job_response_properties.py
openapi_client/models/v0038_job_submission.py
openapi_client/models/v0038_job_submission_response.py
openapi_client/models/v0038_jobs_response.py
openapi_client/models/v0038_license.py
openapi_client/models/v0038_licenses.py
openapi_client/models/v0038_meta.py
openapi_client/models/v0038_meta_plugin.py
openapi_client/models/v0038_meta_slurm.py
openapi_client/models/v0038_meta_slurm_version.py
openapi_client/models/v0038_node.py
openapi_client/models/v0038_node_allocation.py
openapi_client/models/v0038_node_allocation_sockets.py
openapi_client/models/v0038_nodes_response.py
openapi_client/models/v0038_partition.py
openapi_client/models/v0038_partitions_response.py
openapi_client/models/v0038_ping.py
openapi_client/models/v0038_pings.py
openapi_client/models/v0038_reservation.py
openapi_client/models/v0038_reservation_purge_completed.py
openapi_client/models/v0038_reservations_response.py
openapi_client/models/v0038_signal.py
openapi_slurm_0.0.38_client-1.0.0.dist-info/METADATA
openapi_slurm_0.0.38_client-1.0.0.dist-info/WHEEL
openapi_slurm_0.0.38_client-1.0.0.dist-info/top_level.txt
openapi_slurm_0.0.38_client-1.0.0.dist-info/RECORD
