Metadata-Version: 2.1
Name: openapi-slurm-0.0.38-client
Version: 1.0.0
Summary: Slurm Rest API
Home-page: 
Author: SchedMD LLC
Author-email: sales@schedmd.com
License: Apache 2.0
Keywords: OpenAPI,OpenAPI-Generator,Slurm Rest API
Requires-Dist: urllib3 <2.1.0,>=1.25.3
Requires-Dist: python-dateutil
Requires-Dist: pydantic >=2
Requires-Dist: typing-extensions >=4.7.1
